core_system_grpc/__init__.py
core_system_grpc/functions.py
core_system_grpc/messages/__init__.py
core_system_grpc/messages/common/__init__.py
core_system_grpc/messages/common/pagination_pb2.py
core_system_grpc/messages/common/pagination_pb2.pyi
core_system_grpc/messages/common/pagination_pb2_grpc.py
core_system_grpc/messages/common/search_pb2.py
core_system_grpc/messages/common/search_pb2.pyi
core_system_grpc/messages/common/search_pb2_grpc.py
core_system_grpc/messages/customer/common_pb2.py
core_system_grpc/messages/customer/common_pb2.pyi
core_system_grpc/messages/customer/common_pb2_grpc.py
core_system_grpc/messages/customer/request_pb2.py
core_system_grpc/messages/customer/request_pb2.pyi
core_system_grpc/messages/customer/request_pb2_grpc.py
core_system_grpc/messages/customer/response_pb2.py
core_system_grpc/messages/customer/response_pb2.pyi
core_system_grpc/messages/customer/response_pb2_grpc.py
core_system_grpc/messages/order/common_pb2.py
core_system_grpc/messages/order/common_pb2.pyi
core_system_grpc/messages/order/common_pb2_grpc.py
core_system_grpc/messages/order/request_pb2.py
core_system_grpc/messages/order/request_pb2.pyi
core_system_grpc/messages/order/request_pb2_grpc.py
core_system_grpc/messages/order/response_pb2.py
core_system_grpc/messages/order/response_pb2.pyi
core_system_grpc/messages/order/response_pb2_grpc.py
core_system_grpc/messages/product/__init__.py
core_system_grpc/messages/product/common_pb2.py
core_system_grpc/messages/product/common_pb2.pyi
core_system_grpc/messages/product/common_pb2_grpc.py
core_system_grpc/messages/product/request_pb2.py
core_system_grpc/messages/product/request_pb2.pyi
core_system_grpc/messages/product/request_pb2_grpc.py
core_system_grpc/messages/product/response_pb2.py
core_system_grpc/messages/product/response_pb2.pyi
core_system_grpc/messages/product/response_pb2_grpc.py
core_system_grpc/messages/shop/common_pb2.py
core_system_grpc/messages/shop/common_pb2.pyi
core_system_grpc-1.0.0.dist-info/METADATA
core_system_grpc-1.0.0.dist-info/WHEEL
core_system_grpc-1.0.0.dist-info/RECORD
