Metadata-Version: 2.4
Name: core-system-grpc
Version: 1.0.0
Summary: Core System gRPC Package - Python Proto Specifications and Client Libraries
Project-URL: Repository, https://github.com/SaladLabInc/core-system-grpc
Project-URL: Issues, https://github.com/SaladLabInc/core-system-grpc/issues
Author-email: Core System Team <info@alph.kr>
License: Closed Source
Requires-Python: >=3.11
Requires-Dist: grpcio>=1.74.0
Requires-Dist: protobuf>=4.21.0
Provides-Extra: dev
Requires-Dist: grpcio-tools>=1.74.0; extra == 'dev'
Requires-Dist: mypy-protobuf>=3.4.0; extra == 'dev'
